adaptyper/__init__.py
adaptyper/conversion.py
adaptyper-0.4.2.dist-info/METADATA
adaptyper-0.4.2.dist-info/WHEEL
adaptyper-0.4.2.dist-info/RECORD
