Metadata-Version: 2.1
Name: adaptyper
Version: 0.4.2
Summary: Старается конвертировать один тип данных в другой.
Author: max40in
Author-email: mc92mc@yandex.ru
Requires-Python: >=3.11,<4.0
Classifier: Programming Language :: Python :: 3
Classifier: Programming Language :: Python :: 3.11
Classifier: Programming Language :: Python :: 3.12
Classifier: Programming Language :: Python :: 3.13
